[{"title":"Cake","imgUrl":"https://images.unsplash.com/photo-1641577492285-df7ff15218fc?ixlib=rb-1.2.1&ixid=MnwxMjA3fDB8MHxwaG90by1wYWdlfHx8fGVufDB8fHx8&auto=format&fit=crop&w=1170&q=80","price":"250","description":"this is cake of creamy family.\r\n","id":"0.18346984621280193"},{"title":"Beauty","imgUrl":"https://images.unsplash.com/photo-1641592830133-ce6e810b9df3?ixlib=rb-1.2.1&ixid=MnwxMjA3fDB8MHxwaG90by1wYWdlfHx8fGVufDB8fHx8&auto=format&fit=crop&w=387&q=80","price":"6000","description":"yar 6000 me to rasian aati hai","id":"0.8755632255901442"},{"title":"bird","imgUrl":"https://images.unsplash.com/photo-1641575150772-caac11596690?ixlib=rb-1.2.1&ixid=MnwxMjA3fDB8MHxwaG90by1wYWdlfHx8fGVufDB8fHx8&auto=format&fit=crop&w=1170&q=80","price":"500","description":"This is description of the productas.","id":"0.10846195607023357"},{"title":"Sexy Woomen","imgUrl":"https://images.unsplash.com/photo-1641671135777-e5f86bb8e423?ixlib=rb-1.2.1&ixid=MnwxMjA3fDB8MHxwaG90by1wYWdlfHx8fGVufDB8fHx8&auto=format&fit=crop&w=387&q=80","price":"150","description":"This is sexy women.","id":"0.009628143862934868"}]